MANIFEST.in
README
setup.py
django_rpy2/__init__.py
django_rpy2/admin.py
django_rpy2/core.py
django_rpy2/forms.py
django_rpy2/models.py
django_rpy2/settings.py
django_rpy2/tests.py
django_rpy2/urls.py
django_rpy2/views.py
django_rpy2.egg-info/PKG-INFO
django_rpy2.egg-info/SOURCES.txt
django_rpy2.egg-info/dependency_links.txt
django_rpy2.egg-info/requires.txt
django_rpy2.egg-info/top_level.txt
django_rpy2/management/__init__.py
django_rpy2/management/commands/__init__.py
django_rpy2/management/commands/install_r_libs.py
django_rpy2/migrations/0001_initial.py
django_rpy2/migrations/0002_scriptresult_error.py
django_rpy2/migrations/0003_auto_20150401_1517.py
django_rpy2/migrations/0004_resultfiles.py
django_rpy2/migrations/0005_auto_20150722_1546.py
django_rpy2/migrations/__init__.py
django_rpy2/static/css/no-inline-label.css