Metadata-Version: 1.0
Name: django-rpy2
Version: 0.7.1
Summary: Allow django to create R scripts and generate charts and other data output from those scripts.
Home-page: https://bitbucket.net/charts
Author: Martin Owens
Author-email: doctormo@gmail.com
License: AGPLv3
Platform: linux
